{
  "main": {
    "id": "d13895f6521df668",
    "type": "split",
    "children": [
      {
        "id": "9d8dd2d5eaaacf03",
        "type": "tabs",
        "children": [
          {
            "id": "e47e0a2775de62e7",
            "type": "leaf",
            "state": {
              "type": "markdown",
              "state": {
                "file": "Лекции_по_Python_Практика/Восьмая лекция.md",
                "mode": "source",
                "source": false
              },
              "icon": "lucide-file",
              "title": "Восьмая лекция"
            }
          }
        ]
      }
    ],
    "direction": "vertical"
  },
  "left": {
    "id": "c53d5f609e7303c8",
    "type": "split",
    "children": [
      {
        "id": "564e6d223bc0cab8",
        "type": "tabs",
        "children": [
          {
            "id": "4773061883bc0d1e",
            "type": "leaf",
            "state": {
              "type": "file-explorer",
              "state": {
                "sortOrder": "alphabetical"
              },
              "icon": "lucide-folder-closed",
              "title": "Файловый менеджер"
            }
          },
          {
            "id": "42d357da49690bba",
            "type": "leaf",
            "state": {
              "type": "search",
              "state": {
                "query": "",
                "matchingCase": false,
                "explainSearch": false,
                "collapseAll": false,
                "extraContext": false,
                "sortOrder": "alphabetical"
              },
              "icon": "lucide-search",
              "title": "Поиск"
            }
          },
          {
            "id": "bcaf42fc4d7deca9",
            "type": "leaf",
            "state": {
              "type": "bookmarks",
              "state": {},
              "icon": "lucide-bookmark",
              "title": "Закладки"
            }
          }
        ]
      }
    ],
    "direction": "horizontal",
    "width": 300
  },
  "right": {
    "id": "ed44abb146433b94",
    "type": "split",
    "children": [
      {
        "id": "27648cdb27f76370",
        "type": "tabs",
        "children": [
          {
            "id": "aaa16ceb24f6cfe5",
            "type": "leaf",
            "state": {
              "type": "backlink",
              "state": {
                "file": "Справочник по JAVA(Любимка).md",
                "collapseAll": false,
                "extraContext": false,
                "sortOrder": "alphabetical",
                "showSearch": false,
                "searchQuery": "",
                "backlinkCollapsed": false,
                "unlinkedCollapsed": true
              },
              "icon": "links-coming-in",
              "title": "Обратные ссылки для Справочник по JAVA(Любимка)"
            }
          },
          {
            "id": "cd9541bcc7bd8c68",
            "type": "leaf",
            "state": {
              "type": "outgoing-link",
              "state": {
                "file": "Справочник по JAVA(Любимка).md",
                "linksCollapsed": false,
                "unlinkedCollapsed": true
              },
              "icon": "links-going-out",
              "title": "Исходящие ссылки из Справочник по JAVA(Любимка)"
            }
          },
          {
            "id": "d5df9ce6df02c039",
            "type": "leaf",
            "state": {
              "type": "tag",
              "state": {
                "sortOrder": "frequency",
                "useHierarchy": true
              },
              "icon": "lucide-tags",
              "title": "Теги"
            }
          },
          {
            "id": "b2ede9c05ae32bd2",
            "type": "leaf",
            "state": {
              "type": "outline",
              "state": {
                "file": "Справочник по JAVA(Любимка).md"
              },
              "icon": "lucide-list",
              "title": "Структура Справочник по JAVA(Любимка)"
            }
          }
        ]
      }
    ],
    "direction": "horizontal",
    "width": 300,
    "collapsed": true
  },
  "left-ribbon": {
    "hiddenItems": {
      "switcher:Меню быстрого перехода": false,
      "graph:Граф": false,
      "canvas:Создать новый холст": false,
      "daily-notes:Сегодняшняя заметка": false,
      "templates:Вставить шаблон": false,
      "command-palette:Открыть палитру команд": false
    }
  },
  "active": "e47e0a2775de62e7",
  "lastOpenFiles": [
    "JAVA_ADVANCED_NOTICE/Справочник по JAVA(Любимка).md",
    "Лекции_по_Python_Практика/Восьмая лекция.md",
    "Лекции_по_Python_Практика/1.Оглавление.md",
    "Лекции_по_Python_Практика/Шестая лекция.md",
    "Лекции_по_Python_Практика/Шестая.md",
    "Notice/Лекции_по_Python_Практика/Шестая лекция.md",
    "Notice/Лекции_по_Python_Практика/Четвертая лекция.md",
    "Notice/Лекции_по_Python_Практика/Третья Лекция(Алгоритмы).md",
    "Notice/Лекции_по_Python_Практика/Седьмая лекция.md",
    "Notice/Лекции_по_Python_Практика/Пятая Лекция(Циклы).md",
    "Notice/Лекции_по_Python_Практика/Практика6(Знаки Сравнения).md",
    "Notice/Лекции_по_Python_Практика/Практика5(форматирование).md",
    "Notice/Лекции_по_Python_Практика/Практика4(Тесты, формат. вывод).md",
    "Notice/Лекции_по_Python_Практика/Практика3(Округление).md",
    "Notice/Лекции_по_Python_Практика/Практика(Программирование на Python).md",
    "Notice/Лекции_по_Python_Практика/Немного функций в Python(+Библиотеки).md",
    "Notice/Лекции_по_Python_Практика/Вторая лекция(Math, Функции, Коллекции).md",
    "Notice/Лекции_по_Python_Практика/1.Оглавление.md",
    "Notice/Лекции_по_Python_Практика",
    "Notice/Картинки/Pasted image 20241003144704.png",
    "Notice/Картинки/Pasted image 20241003144007.png",
    "Notice/Картинки/Pasted image 20240930093634.png",
    "Notice/Картинки/Pasted image 20240930092907.png",
    "Notice/Картинки/Pasted image 20240925100213.png",
    "Notice/Картинки/Pasted image 20240923083447.png",
    "Notice/Картинки/Pasted image 20240923083336.png",
    "Notice/Картинки",
    "Notice/Scala(Laz)_Обучение/Циклы-практика.md",
    "Notice/Scala(Laz)_Обучение/Циклы, if-else, match,try-catch.md",
    "Notice/Scala(Laz)_Обучение/Строковая интерполяция.md",
    "Notice/Scala(Laz)_Обучение/Переменные и типы данных.md",
    "Notice/Scala(Laz)_Обучение/Моделирование данных(ООП, ФП).md",
    "Notice/Scala(Laz)_Обучение/Методы.md",
    "Notice/Scala(Laz)_Обучение/Базовые функции(Hello world, запуск кода, ввод).md",
    "Notice/Scala(Laz)_Обучение/1.Оглавление.md",
    "Notice/Scala(Laz)_Обучение",
    "Notice/NotionNotices/Справочник по C-ШАРП/Untitled.png",
    "Notice/NotionNotices/Справочник по C-ШАРП",
    "Notice/NotionNotices/ЕГЭ",
    "Notice/NotionNotices/JAAAVAAAA_NOTICES_ADVANCED",
    "Notice/NotionNotices/Home",
    "Notice/NotionNotices",
    "NotionNotices/JAAAVAAAA_NOTICES_ADVANCED",
    "Notice"
  ]
}